passagemath_objects/__init__.py
passagemath_objects-10.6.47.dist-info/DELVEWHEEL
passagemath_objects-10.6.47.dist-info/METADATA
passagemath_objects-10.6.47.dist-info/RECORD
passagemath_objects-10.6.47.dist-info/top_level.txt
passagemath_objects-10.6.47.dist-info/WHEEL
passagemath_objects.libs/libgmp-10-6a8fe126122672a8aed2558e30454e74.dll
sage/all__sagemath_objects.py
sage/arith/all__sagemath_objects.py
sage/arith/long.pxd
sage/arith/numerical_approx.cp314-win_amd64.pyd
sage/arith/numerical_approx.pxd
sage/arith/numerical_approx.pyx
sage/arith/power.cp314-win_amd64.pyd
sage/arith/power.pxd
sage/arith/power.pyx
sage/categories/action.cp314-win_amd64.pyd
sage/categories/action.pxd
sage/categories/action.pyx
sage/categories/algebra_functor.py
sage/categories/all__sagemath_objects.py
sage/categories/basic.py
sage/categories/cartesian_product.py
sage/categories/category.py
sage/categories/category_cy_helper.cp314-win_amd64.pyd
sage/categories/category_cy_helper.pxd
sage/categories/category_cy_helper.pyx
sage/categories/category_singleton.cp314-win_amd64.pyd
sage/categories/category_singleton.pxd
sage/categories/category_singleton.pyx
sage/categories/category_types.py
sage/categories/category_with_axiom.py
sage/categories/covariant_functorial_construction.py
sage/categories/facade_sets.py
sage/categories/functor.cp314-win_amd64.pyd
sage/categories/functor.pxd
sage/categories/functor.pyx
sage/categories/homset.py
sage/categories/homsets.py
sage/categories/isomorphic_objects.py
sage/categories/map.cp314-win_amd64.pyd
sage/categories/map.pxd
sage/categories/map.pyx
sage/categories/morphism.cp314-win_amd64.pyd
sage/categories/morphism.pxd
sage/categories/morphism.pyx
sage/categories/objects.py
sage/categories/primer.py
sage/categories/pushout.py
sage/categories/quotients.py
sage/categories/realizations.py
sage/categories/sets_cat.py
sage/categories/sets_with_partial_maps.py
sage/categories/subobjects.py
sage/categories/subquotients.py
sage/categories/with_realizations.py
sage/cpython/all.py
sage/cpython/atexit.cp314-win_amd64.pyd
sage/cpython/atexit.pyx
sage/cpython/builtin_types.cp314-win_amd64.pyd
sage/cpython/builtin_types.pyx
sage/cpython/cython_metaclass.cp314-win_amd64.pyd
